setup.py
django_simple_version.egg-info/PKG-INFO
django_simple_version.egg-info/SOURCES.txt
django_simple_version.egg-info/dependency_links.txt
django_simple_version.egg-info/top_level.txt
djsimpleversion/__init__.py