Metadata-Version: 1.0
Name: django-simple-version
Version: 0.0.1
Summary: django-simple-version
Home-page: https://github.com/lvjiyong/django-simple-version
Author: lvjiyong
Author-email: lvjiyong@gmail.com
License: Apache2.0
Platform: any
